<annotation>
	<folder>collectedimages</folder>
	<filename>no.3d9cc3d8-0d14-11ef-bf42-005056c00008.jpg</filename>
	<path>D:\machine learning\sign to voice\Sign-to-voice-translation\Tensorflow\workspace\images\collectedimages\no.3d9cc3d8-0d14-11ef-bf42-005056c00008.jpg</path>
	<source>
		<database>Unknown</database>
	</source>
	<size>
		<width>640</width>
		<height>480</height>
		<depth>3</depth>
	</size>
	<segmented>0</segmented>
	<object>
		<name>No</name>
		<pose>Unspecified</pose>
		<truncated>0</truncated>
		<difficult>0</difficult>
		<bndbox>
			<xmin>321</xmin>
			<ymin>96</ymin>
			<xmax>488</xmax>
			<ymax>235</ymax>
		</bndbox>
	</object>
</annotation>
